bench/__init__.py
bench/assets/banner.png
bench/cli.py
bench/dash.py
bench/db.py
bench/pipeline.py
bench/sql/copy.sql
bench/sql/create_tables.sql
bench/sql/create_temp_tables.sql
bench/sql/find_columns.sql
bench/sql/merge.sql
bench/sql/merge_stock.sql
bench/sql/update_fk.sql
bench/stock.py
bench_cli-0.1.6.dist-info/entry_points.txt
bench_cli-0.1.6.dist-info/LICENSE.txt
bench_cli-0.1.6.dist-info/WHEEL
bench_cli-0.1.6.dist-info/METADATA
bench_cli-0.1.6.dist-info/RECORD
